[
    {"name": "Autogenerated", "latitude": 52.57583, "longitude": 6.61944},
    {"name": "Autogenerated", "latitude": 53.20139, "longitude": 5.80859},
    {"name": "Autogenerated", "latitude": 51.05, "longitude": 3.71667},
    {"name": "Autogenerated", "latitude": 51.44083, "longitude": 5.47778},
    {"name": "Autogenerated", "latitude": 51.83333, "longitude": 4.13333},
    {"name": "Autogenerated", "latitude": 51.8425, "longitude": 5.85278},
    {"name": "Autogenerated", "latitude": 52.07667, "longitude": 4.29861},
    {"name": "Autogenerated", "latitude": 53.33, "longitude": 6.91806},
    {"name": "Autogenerated", "latitude": 52.09083, "longitude": 5.12222},
    {"name": "Autogenerated", "latitude": 53.16167, "longitude": 6.76111},
    {"name": "Autogenerated", "latitude": 50.88365, "longitude": 5.98154},
    {"name": "Autogenerated", "latitude": 51.55551, "longitude": 5.0913},
    {"name": "Autogenerated", "latitude": 53.03297, "longitude": 5.6589},
    {"name": "Autogenerated", "latitude": 52.37403, "longitude": 4.88969},
    {"name": "Autogenerated", "latitude": 51.765, "longitude": 5.51806},
    {"name": "Autogenerated", "latitude": 52.6425, "longitude": 5.05972},
    {"name": "Autogenerated", "latitude": 52.22333, "longitude": 5.17639},
    {"name": "Autogenerated", "latitude": 52.555, "longitude": 5.91111},
    {"name": "Autogenerated", "latitude": 51.07947, "longitude": 6.31531},
    {"name": "Autogenerated", "latitude": 52.01667, "longitude": 4.70833},
    {"name": "Autogenerated", "latitude": 51.32254, "longitude": 4.94471},
    {"name": "Autogenerated", "latitude": 51.98, "longitude": 5.91111},
    {"name": "Autogenerated", "latitude": 52.77167, "longitude": 5.10556},
    {"name": "Autogenerated", "latitude": 52.51167, "longitude": 6.25694},
    {"name": "Autogenerated", "latitude": 53.07738, "longitude": 7.40444},
    {"name": "Autogenerated", "latitude": 51.48167, "longitude": 5.66111},
    {"name": "Autogenerated", "latitude": 52.7225, "longitude": 6.47639},
    {"name": "Autogenerated", "latitude": 52.77917, "longitude": 6.90694},
    {"name": "Autogenerated", "latitude": 51.20737, "longitude": 3.44511},
    {"name": "Autogenerated", "latitude": 50.84833, "longitude": 5.68889},
    {"name": "Autogenerated", "latitude": 51.53083, "longitude": 4.46528},
    {"name": "Autogenerated", "latitude": 51.9225, "longitude": 4.47917},
    {"name": "Autogenerated", "latitude": 52.21833, "longitude": 6.89583},
    {"name": "Autogenerated", "latitude": 52.03333, "longitude": 5.65833},
    {"name": "Autogenerated", "latitude": 52.71083, "longitude": 5.74861},
    {"name": "Autogenerated", "latitude": 53.17477, "longitude": 5.42244},
    {"name": "Autogenerated", "latitude": 51.5, "longitude": 3.61389},
    {"name": "Autogenerated", "latitude": 51.16509, "longitude": 4.1437},
    {"name": "Autogenerated", "latitude": 51.59083, "longitude": 5.32917},
]
